Workbook
Name Matrix_A: #REF!
Name MatrixA: #REF!
Name MatrixB: #REF!
Name MatrixC: #REF!
Name MatrixD: #REF!
Name MatrixE: #REF!
Name MatrixF: #REF!
Name VektorB: #REF!
Name VektorC: #REF!

Sheet Primäre_GK
D1: Vorkostenstellen | G1: Endkostenstellen
A2: Kostenart | B2: Kostenbetrag [€] | C2: Verteilungsbasis | D2: Energie | E2: Gebäude | F2: Instandhaltung | G2: Material | H2: Fertigung | I2: Verwaltung | J2: Vertrieb | K2: Gesamt
A3: Gehälter | B3: 454000 | C3: direkt zurechenbar | D3: 3600 | E3: 16800 | F3: 20000 | G3: 12000 | H3: 162000 | I3: 153600 | J3: 86000 | K3: =SUM(D3:J3) -> 454000
A4: Hilfslöhne | B4: 196000 | C4: Arbeitsstunden [h] | D4: 100 | E4: 300 | F4: 3000 | G4: 4000 | H4: 6000 | I4: 200 | J4: 400 | K4: =SUM(D4:J4) -> 14000
A5: Abschreibungen | B5: 360000 | C5: direkt zurechenbar | D5: 4000 | E5: 42000 | F5: 34000 | G5: 40000 | H5: 190000 | I5: 25600 | J5: 24400 | K5: =SUM(D5:J5) -> 360000
A6: Zinsen | B6: 300000 | C6: investiertes Kapital [€] | D6: 100000 | E6: 3700000 | F6: 2400000 | G6: 3200000 | H6: 16400000 | I6: 1800000 | J6: 2400000 | K6: =SUM(D6:J6) -> 30000000
C8: Hilfslöhne pro h | D8: =B4/K4 -> 14
C9: Zinsen pro € Kapital | D9: =B6/K6 -> 0.01
D10: Vorkostenstellen | G10: Endkostenstellen
A11: Kostenart | B11: Kostenbetrag | D11: Energie | E11: Gebäude | F11: Instandhaltung | G11: Material | H11: Fertigung | I11: Verwaltung | J11: Vertrieb | K11: Gesamt
A12: Gehälter | B12: =B3 -> 454000 | D12: =D3 -> 3600 | E12: =E3 -> 16800 | F12: =F3 -> 20000 | G12: =G3 -> 12000 | H12: =H3 -> 162000 | I12: =I3 -> 153600 | J12: =J3 -> 86000 | K12: =SUM(D12:J12) -> 454000
A13: Hilfslöhne | B13: =B4 -> 196000 | D13: =D4*$D$8 -> 1400 | E13: =E4*$D$8 -> 4200 | F13: =F4*$D$8 -> 42000 | G13: =G4*$D$8 -> 56000 | H13: =H4*$D$8 -> 84000 | I13: =I4*$D$8 -> 2800 | J13: =J4*$D$8 -> 5600 | K13: =SUM(D13:J13) -> 196000
A14: Abschreibungen | B14: =B5 -> 360000 | D14: =D5 -> 4000 | E14: =E5 -> 42000 | F14: =F5 -> 34000 | G14: =G5 -> 40000 | H14: =H5 -> 190000 | I14: =I5 -> 25600 | J14: =J5 -> 24400 | K14: =SUM(D14:J14) -> 360000
A15: Zinsen | B15: =B6 -> 300000 | D15: =D6*$D$9 -> 1000 | E15: =E6*$D$9 -> 37000 | F15: =F6*$D$9 -> 24000 | G15: =G6*$D$9 -> 32000 | H15: =H6*$D$9 -> 164000 | I15: =I6*$D$9 -> 18000 | J15: =J6*$D$9 -> 24000 | K15: =SUM(D15:J15) -> 300000
A17: Primäre Gemeinkosten | B17: =SUM(B12:B15) -> 1310000 | D17: =SUM(D12:D15) -> 10000 | E17: =SUM(E12:E15) -> 100000 | F17: =SUM(F12:F15) -> 120000 | G17: =SUM(G12:G15) -> 140000 | H17: =SUM(H12:H15) -> 600000 | I17: =SUM(I12:I15) -> 200000 | J17: =SUM(J12:J15) -> 140000

Sheet Leistungsbeziehungen
B1: Vorkostenstellen | E1: Endkostenstellen
B2: Energie | C2: Gebäude | D2: Instandhaltung | E2: Material | F2: Fertigung | G2: Verwaltung | H2: Vertrieb | I2: Summe
A3: Primäre Gemeinkosten [€] | B3: 10000 | C3: 100000 | D3: 120000 | E3: 140000 | F3: 600000 | G3: 200000 | H3: 140000 | I3: 1310000
A4: Innerbetriebliche Leistungen
A5: Energie [kWh] | B5: 0 | C5: 3000 | D5: 2000 | E5: 20000 | F5: 88000 | G5: 4000 | H5: 3000 | I5: =SUM(B5:H5) -> 120000
A6: Gebäude [m²] | B6: 500 | C6: 400 | D6: 500 | E6: 1000 | F6: 3000 | G6: 600 | H6: 400 | I6: =SUM(B6:H6) -> 6400
A7: Instandhaltung [h] | B7: 350 | C7: 650 | D7: 200 | E7: 1000 | F7: 2100 | G7: 250 | H7: 150 | I7: =SUM(B7:H7) -> 4700

Sheet Gleichungsverfahren Solver
A1: LEISTUNGSBEZIEHUNGEN
B3: Vorkostenstellen | E3: Endkostenstellen
B4: Energie | C4: Gebäude | D4: Instandhaltung | E4: Material | F4: Fertigung | G4: Verwaltung | H4: Vertrieb | I4: Summe
A5: Primäre Gemeinkosten | B5: =Primäre_GK!D17 -> 10000 | C5: =Primäre_GK!E17 -> 100000 | D5: =Primäre_GK!F17 -> 120000 | E5: =Primäre_GK!G17 -> 140000 | F5: =Primäre_GK!H17 -> 600000 | G5: =Primäre_GK!I17 -> 200000 | H5: =Primäre_GK!J17 -> 140000 | I5: =Primäre_GK!K17 -> 0
A6: Innerbetriebliche Leistungen | J6: :.
A7: Energie [kWh] | B7: =Leistungsbeziehungen!B5 -> 0 | C7: =Leistungsbeziehungen!C5 -> 3000 | D7: =Leistungsbeziehungen!D5 -> 2000 | E7: =Leistungsbeziehungen!E5 -> 20000 | F7: =Leistungsbeziehungen!F5 -> 88000 | G7: =Leistungsbeziehungen!G5 -> 4000 | H7: =Leistungsbeziehungen!H5 -> 3000 | I7: =SUM(B7:H7) -> 120000
A8: Gebäude [m²] | B8: =Leistungsbeziehungen!B6 -> 500 | C8: =Leistungsbeziehungen!C6 -> 400 | D8: =Leistungsbeziehungen!D6 -> 500 | E8: =Leistungsbeziehungen!E6 -> 1000 | F8: =Leistungsbeziehungen!F6 -> 3000 | G8: =Leistungsbeziehungen!G6 -> 600 | H8: =Leistungsbeziehungen!H6 -> 400 | I8: =SUM(B8:H8) -> 6400
A9: Instandhaltung [h] | B9: =Leistungsbeziehungen!B7 -> 350 | C9: =Leistungsbeziehungen!C7 -> 650 | D9: =Leistungsbeziehungen!D7 -> 200 | E9: =Leistungsbeziehungen!E7 -> 1000 | F9: =Leistungsbeziehungen!F7 -> 2100 | G9: =Leistungsbeziehungen!G7 -> 250 | H9: =Leistungsbeziehungen!H7 -> 150 | I9: =SUM(B9:H9) -> 4700
D11: Leistungen= | E11: Kosten
A12: Energie €/kWh | B12: 0.25095057 | D12: =I7*B12 -> 30114.068 | E12: =B5+B7*B12+B8*B13+B9*B14 -> 30114.068
A13: Gebäudemiete €/m2 | B13: 19.933048 | D13: =I8*B13 -> 127571.51 | E13: =C5+C7*B12+C8*B13+C9*B14 -> 127571.51
A14: Instandhaltungs €/h | B14: 28.992983 | D14: =I9*B14 -> 136267.02 | E14: =D5+D7*B12+D8*B13+D9*B14 -> 136267.02
B16: Vorkostenstellen | E16: Endkostenstellen
B17: Energie | C17: Gebäude | D17: Instandhaltung | E17: Material | F17: Fertigung | G17: Verwaltung | H17: Vertrieb | I17: Summe
A18: Primäre Gemeinkosten | B18: =B5 -> 10000 | C18: =C5 -> 100000 | D18: =D5 -> 120000 | E18: =E5 -> 140000 | F18: =F5 -> 600000 | G18: =G5 -> 200000 | H18: =H5 -> 140000 | I18: =SUM(B18:H18) -> 1310000
A19: Sekundäre Gemeinkosten
A20: Energie | B20: =B7*$B$12 -> 0 | C20: =C7*$B$12 -> 752.85171 | D20: =D7*$B$12 -> 501.90114 | E20: =E7*$B$12 -> 5019.0114 | F20: =F7*$B$12 -> 22083.65 | G20: =G7*$B$12 -> 1003.8023 | H20: =H7*$B$12 -> 752.85171 | I20: =SUM(B20:H20) -> 30114.068
A21: Gebäude | B21: =B8*$B$13 -> 9966.5242 | C21: =C8*$B$13 -> 7973.2194 | D21: =D8*$B$13 -> 9966.5242 | E21: =E8*$B$13 -> 19933.048 | F21: =F8*$B$13 -> 59799.145 | G21: =G8*$B$13 -> 11959.829 | H21: =H8*$B$13 -> 7973.2194 | I21: =SUM(B21:H21) -> 127571.51
A22: Instandhaltung | B22: =B9*$B$14 -> 10147.544 | C22: =C9*$B$14 -> 18845.439 | D22: =D9*$B$14 -> 5798.5967 | E22: =E9*$B$14 -> 28992.983 | F22: =F9*$B$14 -> 60885.265 | G22: =G9*$B$14 -> 7248.2459 | H22: =H9*$B$14 -> 4348.9475 | I22: =SUM(B22:H22) -> 136267.02
A23: Entlastung (für erbrachte Leistungen) | B23: =-I7*$B$12 -> -30114.068 | C23: =-I8*B13 -> -127571.51 | D23: =-I9*B14 -> -136267.02
A25: Gesamte Gemeinkosten | B25: =SUM(B18:B23) -> 0 | C25: =SUM(C18:C23) -> 0 | D25: =SUM(D18:D23) -> 0 | E25: =SUM(E18:E23) -> 193945.04 | F25: =SUM(F18:F23) -> 742768.06 | G25: =SUM(G18:G23) -> 220211.88 | H25: =SUM(H18:H23) -> 153075.02 | I25: =SUM(B25:H25) -> 1310000
